odoo/addons/portal_partner_select_all/README.rst
odoo/addons/portal_partner_select_all/__init__.py
odoo/addons/portal_partner_select_all/__manifest__.py
odoo/addons/portal_partner_select_all/i18n/portal_partner_select_all.pot
odoo/addons/portal_partner_select_all/readme/CONTRIBUTORS.rst
odoo/addons/portal_partner_select_all/readme/DESCRIPTION.rst
odoo/addons/portal_partner_select_all/readme/USAGE.rst
odoo/addons/portal_partner_select_all/static/description/icon.png
odoo/addons/portal_partner_select_all/static/description/index.html
odoo/addons/portal_partner_select_all/wizard/__init__.py
odoo/addons/portal_partner_select_all/wizard/portal_wizard.py
odoo/addons/portal_partner_select_all/wizard/portal_wizard.xml
odoo11_addon_portal_partner_select_all-11.0.1.0.1.99.dev4.dist-info/METADATA
odoo11_addon_portal_partner_select_all-11.0.1.0.1.99.dev4.dist-info/WHEEL
odoo11_addon_portal_partner_select_all-11.0.1.0.1.99.dev4.dist-info/top_level.txt
odoo11_addon_portal_partner_select_all-11.0.1.0.1.99.dev4.dist-info/RECORD
